realvalidation/__init__.py
realvalidation/__main__.py
realvalidation/argparser.py
realvalidation/constants.py
realvalidation/errors.py
realvalidation/logger.py
realvalidation/realvalidation.py
realvalidation/utils.py
realvalidation/workbook.py
realvalidation-2.0.0.dist-info/AUTHORS
realvalidation-2.0.0.dist-info/LICENSE
realvalidation-2.0.0.dist-info/METADATA
realvalidation-2.0.0.dist-info/WHEEL
realvalidation-2.0.0.dist-info/entry_points.txt
realvalidation-2.0.0.dist-info/pbr.json
realvalidation-2.0.0.dist-info/top_level.txt
realvalidation-2.0.0.dist-info/RECORD
