Metadata-Version: 2.1
Name: realvalidation
Version: 2.0.0
Summary: Python package to interface with RealValidation API.
Home-page: https://github.com/vermilion-tech/python-realvalidation
Author: Kaden Nelson
Author-email: kaden@vermilion.tech
License: MIT
Project-URL: Source Code, https://github.com/vermilion-tech/python-realvalidation
Platform: UNKNOWN
Classifier: Programming Language :: Python :: 3
Classifier: License :: OSI Approved :: MIT License
Classifier: Operating System :: OS Independent
Requires-Dist: requests (==2.21.0)
Requires-Dist: openpyxl (==2.6.0)
Requires-Dist: pbr (==5.1.2)
Requires-Dist: Sphinx (==1.8.4)
Requires-Dist: sphinx-rtd-theme (==0.4.3)
Requires-Dist: twine (==1.13.0)
Requires-Dist: setuptools-scm
